Metadata-Version: 1.0
Name: chinese-tokenizer
Version: 0.0.1
Summary: 哎哟卧槽
Home-page: https://github.com/thsheep/Chinese-tokenizer
Author: 哎哟卧槽
Author-email: admin@youtell.me
License: UNKNOWN
Platform: UNKNOWN
